sbml2julia/__init__.py
sbml2julia/__main__.py
sbml2julia/_version.py
sbml2julia/core.py
sbml2julia-0.1.1.dist-info/LICENSE
sbml2julia-0.1.1.dist-info/METADATA
sbml2julia-0.1.1.dist-info/WHEEL
sbml2julia-0.1.1.dist-info/entry_points.txt
sbml2julia-0.1.1.dist-info/top_level.txt
sbml2julia-0.1.1.dist-info/RECORD
