Metadata-Version: 2.1
Name: sbml2julia
Version: 0.1.1
Summary: Optimization tool based on ODE discretisation.
Home-page: https://github.com/paulflang/sbml2julia
Author: paulflang
Author-email: paul.lang@wolfson.ox.ac.uk
License: MIT
Download-URL: https://github.com/paulflang/sbml2julia
Keywords: Parameter fitting,ODE discretization,Julia,JuMP
Platform: UNKNOWN
Classifier: Development Status :: 3 - Alpha
Classifier: License :: OSI Approved :: MIT License
Classifier: Programming Language :: Python
Classifier: Programming Language :: Python :: 3
Classifier: Natural Language :: English
Classifier: Operating System :: OS Independent
Classifier: Topic :: Scientific/Engineering :: Bio-Informatics
Requires-Dist: cement (>=3.0.0)
Requires-Dist: julia
Requires-Dist: matplotlib
Requires-Dist: numpy
Requires-Dist: openpyxl
Requires-Dist: pandas
Requires-Dist: petab
Requires-Dist: python-libsbml
Requires-Dist: scipy
Requires-Dist: setuptools
